{
    "id": "sustainable-design-hackathon",
    "title": "Sustainable design hackathon",
    "path": "fixed_data/experience/sustainable_design_hackathon",
    "organization": "Various",
    "description": "Detailed documentation and proof for Sustainable design hackathon.",
    "type": "experience",
    "subtype": null,
    "position": null,
    "award": null,
    "score": null,
    "duration": null,
    "place": null,
    "date": {
        "year": 2024,
        "month": null,
        "day": null
    },
    "media": [],
    "tagIds": [],
    "data_folder": "fixed_data/experience/sustainable_design_hackathon"
}